indexpy_auth/__init__.py
indexpy_auth/__version__.py
indexpy_auth/middlewares.py
indexpy_auth/views.py
indexpy_auth-0.1.0.dist-info/LICENSE
indexpy_auth-0.1.0.dist-info/WHEEL
indexpy_auth-0.1.0.dist-info/METADATA
indexpy_auth-0.1.0.dist-info/RECORD
